hanryi/__init__.py
hanryi/hello.py
hanryi_utils-0.0.4.dist-info/LICENSE
hanryi_utils-0.0.4.dist-info/METADATA
hanryi_utils-0.0.4.dist-info/WHEEL
hanryi_utils-0.0.4.dist-info/top_level.txt
hanryi_utils-0.0.4.dist-info/RECORD
