Metadata-Version: 2.1
Name: hanryi-utils
Version: 0.0.4
Summary: Hanryi's private utils.
Home-page: https://github.com/Hanryi/hanryi-utils
Author: Hanryi
Author-email: hanry.rui@gmail.com
Classifier: Programming Language :: Python :: 3
Classifier: License :: OSI Approved :: MIT License
Classifier: Operating System :: OS Independent
Requires-Python: >=3.6
License-File: LICENSE
